genx_ai/__init__.py
genx_ai/api.cpython-312-i386-linux-gnu.so
genx_ai/config.cpython-312-i386-linux-gnu.so
genx_ai/detector.cpython-312-i386-linux-gnu.so
genx_ai/guid.cpython-312-i386-linux-gnu.so
genx_ai/helpers.cpython-312-i386-linux-gnu.so
genx_ai/listener.cpython-312-i386-linux-gnu.so
genx_ai/main.cpython-312-i386-linux-gnu.so
genx_ai/model_manager.cpython-312-i386-linux-gnu.so
genx_ai/profiler.cpython-312-i386-linux-gnu.so
genx_ai/recorder.cpython-312-i386-linux-gnu.so
genx_ai/resource_monitor.cpython-312-i386-linux-gnu.so
genx_ai/roi_filter.cpython-312-i386-linux-gnu.so
genx_ai/rule.cpython-312-i386-linux-gnu.so
genx_ai/schedule.cpython-312-i386-linux-gnu.so
genx_ai/setup.cpython-312-i386-linux-gnu.so
genx_ai/stream.cpython-312-i386-linux-gnu.so
genx_ai/terminal_session.cpython-312-i386-linux-gnu.so
genx_ai/terminal_ui.cpython-312-i386-linux-gnu.so
genx_ai/tracker.cpython-312-i386-linux-gnu.so
genx_ai/worker.cpython-312-i386-linux-gnu.so
genx_ai/service/genx-ai.plist
genx_ai/service/genx-ai.service
genx_ai/service/windows_service.py
genx_ai-2.10.2.dist-info/METADATA
genx_ai-2.10.2.dist-info/WHEEL
genx_ai-2.10.2.dist-info/entry_points.txt
genx_ai-2.10.2.dist-info/top_level.txt
genx_ai-2.10.2.dist-info/RECORD
