Metadata-Version: 2.4
Name: genx-ai
Version: 2.10.2
Summary: AI for industry
Author-email: Jaydeep Ukani <jaydeepukani@outlook.in>, Hardeepsinh Barad <hardeepbarada@gmail.com>
Project-URL: Homepage, https://github.com/jaydeepukani/GenX-AI
Project-URL: Issues, https://github.com/jaydeepukani/GenX-AI/issues
Classifier: Programming Language :: Python :: 3
Requires-Python: >=3.11
Requires-Dist: art>=6.2
Requires-Dist: GPUtil>=1.4.0
Requires-Dist: scipy>=1.14.0
Requires-Dist: imutils>=0.5.4
Requires-Dist: opencv-python-headless>=4.11.0.86
Requires-Dist: opencv-contrib-python-headless>=4.11.0.86
Requires-Dist: psutil>=6.0.0
Requires-Dist: pusher>=3.3.2
Requires-Dist: py-cpuinfo>=9.0.0
Requires-Dist: Pysher>=1.0.8
Requires-Dist: python-dotenv>=1.0.1
Requires-Dist: requests>=2.32.3
Requires-Dist: lapx>=0.5.11.post1
Requires-Dist: ultralytics>=8.3.47
Requires-Dist: wget>=3.2
Requires-Dist: pywin32>=305; platform_system == "Windows"
Requires-Dist: pyzmq>=26.1.0
Requires-Dist: rich>=13.7.1
Requires-Dist: textual>=0.76.0
Requires-Dist: setproctitle>=1.3.5
Requires-Dist: ffmpeg>=1.4
